TallerDeProgramacion/Ejercicio.py
TallerDeProgramacion/__init__.py
TallerProgramacion_Edwar2194682-1.0.0.dist-info/LICENSE.txt
TallerProgramacion_Edwar2194682-1.0.0.dist-info/METADATA
TallerProgramacion_Edwar2194682-1.0.0.dist-info/WHEEL
TallerProgramacion_Edwar2194682-1.0.0.dist-info/top_level.txt
TallerProgramacion_Edwar2194682-1.0.0.dist-info/RECORD
