Metadata-Version: 2.1
Name: TallerProgramacion-Edwar2194682
Version: 1.0.0
Summary: Usamos numpy para desarollar algunos problemas
Author: Edwar Alexis Díaz Rodríguez
License: UNKNOWN
Platform: UNKNOWN
Classifier: Programming Language :: Python :: 3
Classifier: License :: OSI Approved :: MIT License
Classifier: Operating System :: OS Independent
Requires-Python: >=3.9
License-File: LICENSE.txt
Requires-Dist: numpy
